{
	"info": {
		"_postman_id": "cad382c7-ba13-4e5a-8502-1dc37e6c1cd0",
		"name": "cse-api/",
		"description": "Collection of requests for testing the cse-api",
		"schema": "https://schema.getpostman.com/json/collection/v2.1.0/collection.json"
	},
	"item": [
		{
			"name": "target/",
			"event": [
				{
					"listen": "test",
					"script": {
						"id": "3fb1fb27-9f1a-4417-b724-57371608fd82",
						"type": "text/javascript",
						"exec": [
							""
						]
					}
				}
			],
			"request": {
				"auth": {
					"type": "noauth"
				},
				"method": "GET",
				"header": [],
				"body": {
					"mode": "raw",
					"raw": ""
				},
				"url": {
					"raw": "{{api-domain}}/{{target-endpoint}}/{{subject}}/{{grades}}/{{claim}}/{{target}}",
					"host": [
						"{{api-domain}}"
					],
					"path": [
						"{{target-endpoint}}",
						"{{subject}}",
						"{{grades}}",
						"{{claim}}",
						"{{target}}"
					]
				},
				"description": "Returns an ITarget based on grade, subject, claimNumber, and target.shortCode. As of now, none of these arguments can be null."
			},
			"response": []
		},
		{
			"name": "init/",
			"request": {
				"method": "POST",
				"header": [],
				"body": {
					"mode": "raw",
					"raw": ""
				},
				"url": {
					"raw": "{{api-domain}}/{{init-endpoint}}",
					"host": [
						"{{api-domain}}"
					],
					"path": [
						"{{init-endpoint}}"
					]
				},
				"description": "Clears the existing db instance and re-populates in"
			},
			"response": []
		},
		{
			"name": "search/",
			"request": {
				"method": "GET",
				"header": [],
				"body": {
					"mode": "raw",
					"raw": ""
				},
				"url": {
					"raw": "{{api-domain}}/{{search-endpoint}}/?query={{query}}&subject={{subject}}&grades={{grades}}&claimNumber={{claim}}&targetShortCode={{target}}",
					"host": [
						"{{api-domain}}"
					],
					"path": [
						"{{search-endpoint}}",
						""
					],
					"query": [
						{
							"key": "query",
							"value": "{{query}}",
							"description": "A query string that elasticsearch will use to search across alll fields."
						},
						{
							"key": "subject",
							"value": "{{subject}}",
							"description": "The subject, mainly Math or ELA."
						},
						{
							"key": "grades",
							"value": "{{grades}}",
							"description": "A single number or array of numbers representing the grades."
						},
						{
							"key": "claimNumber",
							"value": "{{claim}}"
						},
						{
							"key": "targetShortCode",
							"value": "{{target}}"
						}
					]
				}
			},
			"response": []
		},
		{
			"name": "pdf/",
			"request": {
				"method": "GET",
				"header": [],
				"body": {
					"mode": "raw",
					"raw": ""
				},
				"url": {
					"raw": "{{api-domain}}/{{pdf}}",
					"host": [
						"{{api-domain}}"
					],
					"path": [
						"{{pdf}}"
					]
				}
			},
			"response": []
		},
		{
			"name": "health/",
			"request": {
				"method": "GET",
				"header": [],
				"body": {
					"mode": "raw",
					"raw": ""
				},
				"url": {
					"raw": "{{api-domain}}/{{health-endpoint}}",
					"host": [
						"{{api-domain}}"
					],
					"path": [
						"{{health-endpoint}}"
					]
				},
				"description": "An API Route Health Check"
			},
			"response": []
		}
	],
	"event": [
		{
			"listen": "prerequest",
			"script": {
				"id": "59afedc0-12c2-4fac-897a-40c6b18a619d",
				"type": "text/javascript",
				"exec": [
					""
				]
			}
		},
		{
			"listen": "test",
			"script": {
				"id": "dfb559ce-7f2f-403a-abe6-493f3763776e",
				"type": "text/javascript",
				"exec": [
					""
				]
			}
		}
	],
	"variable": [
		{
			"id": "86de5a73-44c2-4097-921d-0a7df5325944",
			"key": "api-domain",
			"value": "http://localhost:3000",
			"type": "string"
		},
		{
			"id": "62016ea8-c79a-4930-83e8-a5ff6b02987a",
			"key": "pdf-endpoint",
			"value": "api/pdf",
			"type": "string"
		},
		{
			"id": "e3281120-ea4d-41e0-b7ef-49768ac13ede",
			"key": "search-endpoint",
			"value": "api/search",
			"type": "string"
		},
		{
			"id": "492364bf-1773-45b9-9284-063a58054762",
			"key": "init-endpoint",
			"value": "api/init",
			"type": "string"
		},
		{
			"id": "5cc8ac45-6a23-40dc-af5f-e09d9db8325d",
			"key": "target-endpoint",
			"value": "api/target",
			"type": "string"
		},
		{
			"id": "eb4d4ce3-0ef7-4828-82b1-38de5ebb8cd9",
			"key": "subject",
			"value": "Math",
			"type": "string"
		},
		{
			"id": "05d5698f-7c76-4ba9-a595-59fff0c85c18",
			"key": "grades",
			"value": "3",
			"type": "string"
		},
		{
			"id": "264a6ce9-9fd4-4d02-86c0-d99c2fec3685",
			"key": "claim",
			"value": "C2",
			"type": "string"
		},
		{
			"id": "5a22f576-0d16-426b-bd34-c4afaa5d032a",
			"key": "target",
			"value": "M.G3.C1G.TK",
			"type": "string"
		},
		{
			"id": "cef39f4a-0695-418e-86ef-c80b8e71e6e1",
			"key": "query",
			"value": "simple procedure",
			"type": "string"
		},
		{
			"id": "7c68d494-5abd-4ae0-a45e-4332741a5531",
			"key": "health-endpoint",
			"value": "health",
			"type": "string"
		}
	]
}